code_augmentor_support/__init__.py
code_augmentor_support/models.py
code_augmentor_support/tasks.py
code_augmentor_support-2.3.0.dist-info/LICENSE
code_augmentor_support-2.3.0.dist-info/WHEEL
code_augmentor_support-2.3.0.dist-info/METADATA
code_augmentor_support-2.3.0.dist-info/RECORD
