Metadata-Version: 2.1
Name: code-augmentor-support
Version: 2.3.0
Summary: Enables the use of Python 3 to write code generator scripts for Code Augmentor
Home-page: https://github.com/aaronicsubstances/code-augmentor#readme
Keywords: code-generation,data-driven,macro-processor
Author: Aaron Baffour-Awuah
Author-email: aaronbaffourawuah@gmail.com
Requires-Python: >=3.5,<4.0
Classifier: Programming Language :: Python :: 3
Classifier: Programming Language :: Python :: 3.5
Classifier: Programming Language :: Python :: 3.6
Classifier: Programming Language :: Python :: 3.7
Classifier: Programming Language :: Python :: 3.8
Classifier: Programming Language :: Python :: 3.9
Project-URL: Bug Tracker, https://github.com/aaronicsubstances/code-augmentor-python/issues
Project-URL: Repository, https://github.com/aaronicsubstances/code-augmentor-python
